expect_language_server/__init__.py
expect_language_server/__main__.py
expect_language_server/_metainfo.py
expect_language_server/_version.py
expect_language_server/api.py
expect_language_server/py.typed
expect_language_server/server.py
expect_language_server/assets/json/expect.json
expect_language_server-0.0.1.data/data/share/bash-completion/completions/expect-language-server
expect_language_server-0.0.1.data/data/share/man/man1/expect-language-server.1
expect_language_server-0.0.1.data/data/share/zsh/site-functions/_expect-language-server
expect_language_server-0.0.1.dist-info/LICENSE
expect_language_server-0.0.1.dist-info/METADATA
expect_language_server-0.0.1.dist-info/WHEEL
expect_language_server-0.0.1.dist-info/entry_points.txt
expect_language_server-0.0.1.dist-info/top_level.txt
expect_language_server-0.0.1.dist-info/RECORD
