Metadata-Version: 2.1
Name: expect-language-server
Version: 0.0.1
Summary: expect language server
Author-email: Wu Zhenyu <wuzhenyu@ustc.edu>
License: GPL v3
Project-URL: Homepage, https://expect-language-server.readthedocs.io
Project-URL: Download, https://github.com/Freed-Wu/expect-language-server/releases
Project-URL: Bug Report, https://github.com/Freed-Wu/expect-language-server/issues
Project-URL: Source, https://github.com/Freed-Wu/expect-language-server
Keywords: expect,language server
Classifier: Development Status :: 3 - Alpha
Classifier: Intended Audience :: Developers
Classifier: Topic :: Software Development :: Build Tools
Classifier: License :: OSI Approved :: GNU General Public License v3 (GPLv3)
Classifier: Operating System :: Microsoft :: Windows
Classifier: Operating System :: POSIX
Classifier: Operating System :: Unix
Classifier: Operating System :: MacOS
Classifier: Programming Language :: Python :: 3 :: Only
Classifier: Programming Language :: Python :: 3
Classifier: Programming Language :: Python :: 3.7
Classifier: Programming Language :: Python :: 3.8
Classifier: Programming Language :: Python :: 3.9
Classifier: Programming Language :: Python :: 3.10
Classifier: Programming Language :: Python :: 3.11
Classifier: Programming Language :: Python :: Implementation :: CPython
Classifier: Programming Language :: Python :: Implementation :: PyPy
Requires-Python: >=3.7
License-File: LICENSE
Requires-Dist: platformdirs
Requires-Dist: pygls
Provides-Extra: cache
Requires-Dist: markdown-it-py ; extra == 'cache'
Requires-Dist: pypandoc ; extra == 'cache'
Provides-Extra: dev
Requires-Dist: pytest-cov ; extra == 'dev'
